object_get/__init__.py
object_get/main.py
object_get-0.0.1.dist-info/LICENSE
object_get-0.0.1.dist-info/METADATA
object_get-0.0.1.dist-info/WHEEL
object_get-0.0.1.dist-info/top_level.txt
object_get-0.0.1.dist-info/RECORD
