Metadata-Version: 2.1
Name: object-get
Version: 0.0.1
Summary: Use "." to get the value of a JSON object. Just like JavaScripthat gets the value of an object
Home-page: https://github.com/Lete114/python-object-get
Author: Lete114
Author-email: mylete114@gmail.com
License: MIT
License-File: LICENSE
